mosaik/__init__.py
mosaik/_debug.py
mosaik/_version.py
mosaik/exceptions.py
mosaik/scenario.py
mosaik/scheduler.py
mosaik/simmanager.py
mosaik/util.py
tests/fixtures/__init__.py
tests/fixtures/scenario_1.py
tests/fixtures/scenario_2.py
tests/fixtures/scenario_3.py
tests/fixtures/scenario_4.py
tests/fixtures/scenario_5.py
tests/fixtures/scenario_6.py
tests/mocks/__init__.py
tests/mocks/simulator_mock.py
mosaik.Core_SemVer-2.5.3rc20230505130344.dist-info/AUTHORS.txt
mosaik.Core_SemVer-2.5.3rc20230505130344.dist-info/LICENSE.txt
mosaik.Core_SemVer-2.5.3rc20230505130344.dist-info/METADATA
mosaik.Core_SemVer-2.5.3rc20230505130344.dist-info/WHEEL
mosaik.Core_SemVer-2.5.3rc20230505130344.dist-info/entry_points.txt
mosaik.Core_SemVer-2.5.3rc20230505130344.dist-info/top_level.txt
mosaik.Core_SemVer-2.5.3rc20230505130344.dist-info/RECORD
