Metadata-Version: 2.1
Name: mosaik.Core-SemVer
Version: 2.5.3rc20230505130344
Summary: Mosaik is a flexible Smart-Grid co-simulation framework.
Home-page: https://mosaik.offis.de
Author: Stefan Scherfke
Author-email: mosaik@offis.de
Maintainer: Bengt Lüers
Maintainer-email: bengt.lueers@gmail.com
License: UNKNOWN
Platform: UNKNOWN
Classifier: Development Status :: 5 - Production/Stable
Classifier: Environment :: Console
Classifier: Intended Audience :: Science/Research
Classifier: Natural Language :: English
Classifier: License :: OSI Approved :: GNU Lesser General Public License v2 (LGPLv2)
Classifier: Natural Language :: English
Classifier: Operating System :: OS Independent
Classifier: Programming Language :: Python
Classifier: Programming Language :: Python :: 3
Classifier: Programming Language :: Python :: 3.7
Classifier: Programming Language :: Python :: 3.8
Classifier: Programming Language :: Python :: 3.9
Classifier: Topic :: Scientific/Engineering
Classifier: Topic :: Software Development :: Libraries :: Python Modules
Requires-Dist: networkx (>=2.4)
Requires-Dist: mosaik.API-SemVer (>=2.4.2rc20190716091443)
Requires-Dist: mosaik.Core-SemVer (>=2.5.2rc20190715231038)
Requires-Dist: simpy (>=3.0.10)
Requires-Dist: simpy.io (>=0.2.3)
